{"stat.mineBlock.minecraft.stonebrick":1642,"stat.pickup.minecraft.sandstone":60,"stat.useItem.minecraft.fence_gate":17,"stat.pickup.minecraft.chest":34,"stat.mineBlock.minecraft.netherrack":1728,"stat.enderchestOpened":116,"stat.useItem.minecraft.stone_button":4,"stat.drop.minecraft.glass_bottle":2,"stat.mineBlock.minecraft.glass":6,"stat.pickup.minecraft.wooden_door":8,"stat.pickup.minecraft.coal_block":3,"stat.pickup.minecraft.nether_brick":12,"stat.drop.minecraft.glowstone_dust":2,"stat.craftItem.minecraft.wooden_hoe":1,"stat.craftingTableInteraction":345,"stat.useItem.minecraft.minecart":12,"stat.useItem.minecraft.iron_shovel":3005,"stat.craftItem.minecraft.spruce_door":6,"stat.crouchOneCm":476529,"stat.pickup.minecraft.rotten_flesh":2067,"stat.drop.minecraft.rotten_flesh":18,"stat.breakItem.minecraft.flint_and_steel":1,"stat.useItem.minecraft.spruce_boat":21,"stat.useItem.minecraft.spruce_door":12,"stat.mineBlock.minecraft.yellow_flower":16,"stat.drop.minecraft.string":1,"stat.breakItem.minecraft.iron_shovel":11,"stat.pickup.minecraft.gold_nugget":2,"stat.useItem.minecraft.chest":117,"stat.pickup.minecraft.leather_leggings":1,"stat.mineBlock.minecraft.furnace":17,"stat.drop.minecraft.sponge":2,"stat.useItem.minecraft.iron_bars":11,"stat.useItem.minecraft.stone_brick_stairs":1138,"stat.killEntity.Sheep":28,"stat.pickup.minecraft.diamond_helmet":2,"stat.useItem.minecraft.cobblestone":1948,"stat.craftItem.minecraft.iron_sword":5,"stat.pickup.minecraft.wheat":1390,"stat.breakItem.minecraft.iron_axe":5,"stat.pickup.minecraft.melon_seeds":2,"stat.beaconInteraction":6,"stat.craftItem.minecraft.arrow":68,"stat.useItem.minecraft.dark_oak_stairs":268,"achievement.openInventory":4000,"stat.useItem.minecraft.stained_glass":92,"stat.pickup.minecraft.sand":2615,"stat.pickup.minecraft.spruce_boat":18,"stat.pickup.minecraft.iron_door":18,"stat.killEntity.Cow":58,"stat.mineBlock.minecraft.web":40,"stat.useItem.minecraft.stained_glass_pane":582,"stat.craftItem.minecraft.dark_oak_boat":1,"stat.pickup.minecraft.iron_bars":11,"stat.pickup.minecraft.ladder":18,"stat.mineBlock.minecraft.stained_glass":1,"stat.useItem.minecraft.log":811,"stat.mineBlock.minecraft.spruce_stairs":21,"stat.pickup.minecraft.stone_button":4,"stat.craftItem.minecraft.iron_chestplate":5,"stat.mineBlock.minecraft.acacia_fence":6,"stat.craftItem.minecraft.furnace":29,"stat.mineBlock.minecraft.log":1735,"stat.pickup.minecraft.iron_boots":9,"stat.craftItem.minecraft.leather_helmet":2,"stat.pickup.minecraft.melon":3829,"stat.craftItem.minecraft.iron_helmet":7,"stat.mineBlock.minecraft.emerald_ore":4,"stat.pickup.minecraft.log2":869,"stat.craftItem.minecraft.carpet":15,"stat.pickup.minecraft.redstone":619,"stat.craftItem.minecraft.gold_nugget":666,"stat.useItem.minecraft.leaves":463,"stat.craftItem.minecraft.stone_pressure_plate":64,"stat.useItem.minecraft.netherrack":1058,"stat.useItem.minecraft.iron_hoe":309,"stat.pickup.minecraft.sponge":2,"stat.pickup.minecraft.bed":11,"achievement.acquireIron":11,"stat.pickup.minecraft.diamond_shovel":6,"stat.useItem.minecraft.fire_charge":6,"stat.pickup.minecraft.sapling":616,"stat.damageDealt":114726,"stat.pickup.minecraft.stone_brick_stairs":342,"stat.useItem.minecraft.fence":262,"stat.craftItem.minecraft.ender_chest":2,"stat.killEntity.Bat":1,"stat.mineBlock.minecraft.red_mushroom_block":2,"stat.pickup.minecraft.cooked_beef":14,"stat.pickup.minecraft.spider_eye":29,"stat.useItem.minecraft.potato":35,"stat.useItem.minecraft.acacia_door":8,"achievement.exploreAllBiomes":{"value":0,"progress":["Sunflower Plains","Extreme Hills+","Desert","Deep Ocean","Taiga","Flower Forest","Extreme Hills","Ocean","TaigaHills","Plains","Swampland M","Hell","Birch Forest Hills","ForestHills","Forest","DesertHills","Birch Forest","Beach","Roofed Forest","Swampland","River"]},"stat.mineBlock.minecraft.double_plant":22,"stat.craftItem.minecraft.iron_pickaxe":28,"stat.craftItem.minecraft.flint_and_steel":2,"stat.pickup.minecraft.book":902,"stat.pickup.minecraft.quartz":95,"stat.drop.minecraft.shears":1,"stat.craftItem.minecraft.diamond_chestplate":1,"stat.useItem.minecraft.melon_block":2,"stat.useItem.minecraft.anvil":22,"stat.pickup.minecraft.dirt":7772,"stat.craftItem.minecraft.cobblestone_wall":12,"stat.useItem.minecraft.dark_oak_boat":1,"stat.craftItem.minecraft.bed":5,"stat.craftItem.minecraft.wooden_pickaxe":2,"stat.mineBlock.minecraft.sand":2436,"stat.pickup.minecraft.enchanted_book":4,"stat.sneakTime":150072,"stat.pickup.minecraft.coal_ore":452,"stat.craftItem.minecraft.cooked_chicken":362,"stat.mineBlock.minecraft.monster_egg":3,"stat.mineBlock.minecraft.sandstone":55,"stat.mineBlock.minecraft.waterlily":2,"stat.craftItem.minecraft.chest":81,"stat.mineBlock.minecraft.redstone_torch":2,"stat.useItem.minecraft.wooden_door":9,"stat.drop.minecraft.spruce_stairs":1,"stat.useItem.minecraft.experience_bottle":117,"stat.pickup.minecraft.leather_boots":1,"stat.pickup.minecraft.yellow_flower":34,"stat.useItem.minecraft.spruce_fence":154,"stat.drop.minecraft.spruce_fence":43,"stat.trappedChestTriggered":18,"stat.useItem.minecraft.diamond_pickaxe":14122,"stat.pickup.minecraft.iron_block":7,"stat.craftItem.minecraft.fence_gate":6,"stat.pickup.minecraft.gold_ore":145,"stat.useItem.minecraft.tnt":175,"stat.craftItem.minecraft.diamond_block":12,"stat.pickup.minecraft.mutton":36,"stat.pickup.minecraft.glass_pane":63,"stat.useItem.minecraft.diamond_shovel":8263,"stat.useItem.minecraft.snowball":294,"stat.pickup.minecraft.tnt":38,"stat.craftItem.minecraft.torch":1536,"stat.useItem.minecraft.planks":1368,"stat.talkedToVillager":1,"stat.pickup.minecraft.stone_stairs":58,"stat.pickup.minecraft.crafting_table":45,"stat.pickup.minecraft.iron_ingot":120,"stat.craftItem.minecraft.ender_eye":9,"stat.pickup.minecraft.cooked_porkchop":36,"stat.drop.minecraft.dragon_breath":1,"stat.pickup.minecraft.emerald":3,"stat.useItem.minecraft.cooked_chicken":556,"stat.useItem.minecraft.torch":2288,"stat.useItem.minecraft.bed":23,"stat.useItem.minecraft.stone_pickaxe":2378,"stat.pickup.minecraft.netherrack":1723,"stat.drop.minecraft.egg":7,"stat.pickup.minecraft.minecart":18,"stat.craftItem.minecraft.iron_bars":16,"stat.mineBlock.minecraft.gold_ore":131,"stat.pickup.minecraft.anvil":5,"stat.craftItem.minecraft.redstone_block":47,"achievement.buildWorkBench":27,"stat.useItem.minecraft.stone":1093,"stat.craftItem.minecraft.diamond_sword":4,"stat.craftItem.minecraft.iron_leggings":5,"stat.pickup.minecraft.ender_pearl":7,"stat.useItem.minecraft.ladder":86,"stat.pickup.minecraft.enchanting_table":2,"stat.craftItem.minecraft.diamond_leggings":2,"achievement.killCow":6,"stat.useItem.minecraft.redstone":2,"stat.mineBlock.minecraft.stone_stairs":27,"stat.pickup.minecraft.carpet":2,"stat.drop.minecraft.wool":34,"stat.mineBlock.minecraft.bookshelf":165,"stat.pickup.minecraft.beef":116,"stat.pickup.minecraft.cobblestone_wall":1,"stat.mineBlock.minecraft.diamond_ore":45,"stat.pickup.minecraft.ender_chest":2,"stat.mineBlock.minecraft.torch":688,"stat.useItem.minecraft.red_flower":108,"stat.craftItem.minecraft.cooked_beef":111,"stat.pickup.minecraft.milk_bucket":2,"stat.useItem.minecraft.milk_bucket":3,"stat.pickup.minecraft.string":88,"stat.useItem.minecraft.monster_egg":2,"stat.useItem.minecraft.diamond_sword":1556,"stat.pickup.minecraft.diamond":107,"stat.useItem.minecraft.oak_stairs":60,"stat.craftItem.minecraft.ladder":33,"stat.craftItem.minecraft.wooden_shovel":1,"stat.mineBlock.minecraft.carpet":1,"stat.pickup.minecraft.leaves2":34,"stat.pickup.minecraft.snowball":326,"stat.mineBlock.minecraft.wool":1,"stat.breakItem.minecraft.stone_pickaxe":17,"stat.drop.minecraft.wooden_shovel":1,"stat.useItem.minecraft.flower_pot":8,"stat.craftItem.minecraft.spruce_boat":4,"stat.pickup.minecraft.glass":5,"stat.pickup.minecraft.baked_potato":64,"stat.pickup.minecraft.iron_axe":4,"stat.useItem.minecraft.enchanting_table":3,"stat.craftItem.minecraft.quartz_block":23,"stat.climbOneCm":418966,"stat.useItem.minecraft.stone_sword":226,"stat.useItem.minecraft.sapling":425,"stat.drop":408,"stat.mineBlock.minecraft.anvil":5,"stat.pickup.minecraft.sign":16,"stat.drop.minecraft.wooden_hoe":1,"stat.fallOneCm":800463,"stat.craftItem.minecraft.diamond":63,"stat.pickup.minecraft.iron_ore":821,"stat.pickup.minecraft.boat":9,"stat.useItem.minecraft.coal_ore":446,"stat.craftItem.minecraft.sandstone":89,"stat.mineBlock.minecraft.nether_brick":17,"stat.hopperInspected":1,"achievement.buildFurnace":3,"stat.useItem.minecraft.boat":8,"stat.pickup.minecraft.flower_pot":2,"stat.craftItem.minecraft.coal":9,"stat.craftItem.minecraft.bread":218,"stat.pickup.minecraft.diamond_leggings":2,"stat.craftItem.minecraft.cooked_mutton":35,"stat.breakItem.minecraft.wooden_pickaxe":1,"stat.useItem.minecraft.water_bucket":296,"stat.pickup.minecraft.carrot":901,"stat.useItem.minecraft.wheat_seeds":1892,"stat.drop.minecraft.netherrack":2,"stat.pickup.minecraft.birch_fence":1,"stat.mineBlock.minecraft.rail":25,"stat.useItem.minecraft.stonebrick":7476,"stat.useItem.minecraft.melon_seeds":63,"stat.useItem.minecraft.furnace":40,"stat.pickup.minecraft.soul_sand":15,"stat.craftItem.minecraft.acacia_door":6,"stat.mineBlock.minecraft.tnt":20,"stat.craftItem.minecraft.speckled_melon":83,"stat.mineBlock.minecraft.pumpkin":2,"stat.useItem.minecraft.cooked_mutton":22,"stat.useItem.minecraft.melon":46,"stat.craftItem.minecraft.wooden_button":5,"stat.mineBlock.minecraft.vine":7,"achievement.portal":84,"stat.flyOneCm":8658836,"stat.mineBlock.minecraft.chest":26,"achievement.buildPickaxe":41,"stat.mineBlock.minecraft.birch_fence":1,"stat.pickup.minecraft.golden_sword":2,"stat.mineBlock.minecraft.iron_ore":726,"stat.craftItem.minecraft.glowstone":70,"stat.drop.minecraft.filled_map":1,"stat.damageTaken":31662,"stat.pickup.minecraft.coal":1642,"stat.mineBlock.minecraft.prismarine":17,"stat.pickup.minecraft.shield":1,"stat.useItem.minecraft.sponge":2,"stat.entityKilledBy.Spider":2,"stat.mineBlock.minecraft.nether_brick_fence":8,"stat.killEntity.Chicken":583,"stat.mineBlock.minecraft.magma":81,"stat.craftItem.minecraft.stone_pickaxe":24,"stat.mineBlock.minecraft.cobblestone":928,"stat.sleepInBed":49,"stat.useItem.minecraft.stained_hardened_clay":3,"stat.mineBlock.minecraft.iron_bars":11,"stat.useItem.minecraft.dye":11,"stat.craftItem.minecraft.stained_glass_pane":576,"stat.pickup.minecraft.diamond_sword":8,"stat.craftItem.minecraft.leather_boots":2,"stat.mineBlock.minecraft.spruce_fence":22,"stat.pickup.minecraft.gravel":246,"stat.pickup.minecraft.acacia_fence":5,"stat.pickup.minecraft.water_bucket":8,"stat.craftItem.minecraft.melon_seeds":102,"stat.pickup.minecraft.cooked_chicken":393,"stat.entityKilledBy.Creeper":2,"stat.useItem.minecraft.ender_chest":4,"stat.useItem.minecraft.lapis_ore":6,"stat.pickup.minecraft.torch":1101,"stat.useItem.minecraft.log2":1041,"stat.pickup.minecraft.lapis_ore":10,"stat.useItem.minecraft.flint_and_steel":81,"stat.pickup.minecraft.feather":648,"stat.drop.minecraft.stone":137,"stat.pickup.minecraft.diamond_chestplate":2,"stat.mineBlock.minecraft.enchanting_table":2,"stat.pickup.minecraft.grass":33,"stat.breakItem.minecraft.diamond_shovel":3,"stat.pickup.minecraft.porkchop":8,"stat.drop.minecraft.waterlily":6,"stat.craftItem.minecraft.iron_hoe":5,"stat.craftItem.minecraft.iron_axe":11,"stat.useItem.minecraft.spruce_stairs":76,"stat.mineBlock.minecraft.wooden_slab":407,"achievement.makeBread":435,"stat.useItem.minecraft.diamond_ore":29,"stat.pickup.minecraft.ender_eye":7,"stat.pickup.minecraft.chicken":376,"stat.breakItem.minecraft.iron_sword":1,"stat.useItem.minecraft.stone_slab":826,"stat.pickup.minecraft.spruce_stairs":21,"stat.mineBlock.minecraft.fence":160,"stat.useItem.minecraft.cooked_porkchop":35,"stat.mineBlock.minecraft.melon_block":684,"stat.craftItem.minecraft.leather_chestplate":2,"stat.killEntity.Creeper":38,"stat.craftItem.minecraft.iron_block":93,"stat.pickup.minecraft.glass_bottle":8,"stat.mineBlock.minecraft.planks":607,"stat.drop.minecraft.spawn_egg":1,"stat.craftItem.minecraft.stone_slab":798,"stat.leaveGame":98,"stat.craftItem.minecraft.iron_ingot":1266,"stat.drop.minecraft.diamond_sword":1,"stat.craftItem.minecraft.stone_stairs":200,"stat.killEntity.Endermite":2,"stat.pickup.minecraft.planks":699,"stat.useItem.minecraft.ender_eye":6,"stat.mineBlock.minecraft.leaves":1068,"stat.useItem.minecraft.painting":66,"achievement.buildSword":7,"stat.craftItem.minecraft.wooden_door":9,"stat.craftItem.minecraft.birch_fence":12,"achievement.mineWood":2439,"stat.mineBlock.minecraft.red_flower":59,"stat.pickup.minecraft.iron_sword":6,"stat.mineBlock.minecraft.stone_slab":143,"stat.useItem.minecraft.iron_axe":1937,"stat.pickup.minecraft.spruce_door":8,"stat.craftItem.minecraft.dye":126,"stat.pickup.minecraft.quartz_ore":58,"stat.drop.minecraft.carrot":6,"stat.craftItem.minecraft.diamond_pickaxe":9,"stat.pickup.minecraft.log":1963,"stat.useItem.minecraft.acacia_fence":36,"stat.pickup.minecraft.iron_chestplate":5,"stat.pickup.minecraft.wooden_slab":504,"stat.useItem.minecraft.stone_shovel":233,"stat.useItem.minecraft.iron_ore":1,"stat.diveOneCm":721983,"stat.craftItem.minecraft.bow":8,"stat.useItem.minecraft.rotten_flesh":13,"stat.pickup.minecraft.fence_gate":3,"stat.pickup.minecraft.quartz_block":46,"stat.useItem.minecraft.nether_brick":10,"stat.pickup.minecraft.furnace":20,"stat.craftItem.minecraft.wooden_axe":1,"stat.useItem.minecraft.diamond_block":10,"stat.pickup.minecraft.redstone_ore":55,"stat.pickup.minecraft.painting":31,"stat.useItem.minecraft.bow":695,"stat.pickup.minecraft.red_flower":64,"stat.useItem.minecraft.cooked_beef":62,"stat.breakItem.minecraft.diamond_pickaxe":1,"stat.drop.minecraft.feather":5,"stat.pickup.minecraft.leaves":503,"stat.mineBlock.minecraft.crafting_table":45,"stat.drop.minecraft.iron_pickaxe":1,"stat.pickup.minecraft.bow":9,"stat.pickup.minecraft.diamond_pickaxe":14,"stat.pickup.minecraft.reeds":14,"stat.pickup.minecraft.blaze_rod":14,"achievement.diamonds":9,"stat.useItem.minecraft.egg":3564,"stat.craftItem.minecraft.stonebrick":8544,"stat.useItem.minecraft.crafting_table":70,"stat.flowerPotted":6,"stat.craftItem.minecraft.bookshelf":77,"stat.pickup.minecraft.apple":13,"stat.useItem.minecraft.stone_hoe":34,"stat.craftItem.minecraft.dark_oak_stairs":200,"stat.mineBlock.minecraft.obsidian":7,"stat.craftItem.minecraft.diamond_boots":2,"stat.killEntity.Enderman":7,"stat.mineBlock.minecraft.stone_brick_stairs":294,"stat.useItem.minecraft.glass":21,"stat.mineBlock.minecraft.dark_oak_fence":4,"achievement.buildBetterPickaxe":41,"stat.useItem.minecraft.ender_pearl":106,"stat.mineBlock.minecraft.sapling":58,"stat.timeSinceDeath":41607,"stat.pickup.minecraft.iron_leggings":6,"stat.useItem.minecraft.golden_apple":1,"stat.useItem.minecraft.gravel":100,"stat.mineBlock.minecraft.leaves2":66,"stat.killEntity.PigZombie":2,"stat.boatOneCm":3158893,"stat.useItem.minecraft.wool":38,"stat.useItem.minecraft.acacia_stairs":8,"stat.craftItem.minecraft.bucket":24,"stat.pickup.minecraft.stone_pickaxe":5,"achievement.buildHoe":9,"stat.useItem.minecraft.nether_brick_fence":8,"stat.pickup.minecraft.flint":27,"stat.useItem.minecraft.glowstone":129,"stat.pickup.minecraft.stone_shovel":2,"stat.craftItem.minecraft.iron_shovel":15,"stat.mineBlock.minecraft.stone_button":4,"stat.craftItem.minecraft.acacia_fence":51,"stat.pickup.minecraft.stone":6044,"stat.pickup.minecraft.bucket":4,"achievement.killEnemy":2087,"stat.useItem.minecraft.sand":927,"stat.pickup.minecraft.leather_chestplate":1,"stat.mineBlock.minecraft.snow_layer":168,"stat.craftItem.minecraft.fence":75,"stat.playOneMinute":5986137,"stat.useItem.minecraft.redstone_torch":2,"stat.craftItem.minecraft.gold_ingot":121,"stat.killEntity.Pig":6,"stat.useItem.minecraft.birch_fence":13,"stat.drop.minecraft.melon":65,"stat.pickup.minecraft.magma":66,"stat.pickup.minecraft.wool":101,"stat.useItem.minecraft.gold_ore":6,"stat.killEntity.Spider":64,"stat.drop.minecraft.cooked_chicken":7,"stat.drop.minecraft.diamond_pickaxe":2,"stat.mineBlock.minecraft.soul_sand":15,"stat.pickup.minecraft.flint_and_steel":1,"stat.craftItem.minecraft.glass":925,"stat.craftItem.minecraft.stone_shovel":4,"stat.animalsBred":237,"stat.craftItem.minecraft.spruce_stairs":84,"stat.pickup.minecraft.iron_hoe":1,"stat.pickup.minecraft.dark_oak_fence":4,"stat.craftItem.minecraft.stick":1136,"stat.pickup.minecraft.glowstone":119,"stat.drop.minecraft.spider_eye":1,"stat.craftItem.minecraft.acacia_stairs":8,"stat.craftItem.minecraft.wooden_slab":3532,"stat.furnaceInteraction":708,"stat.pickup.minecraft.stick":240,"stat.craftItem.minecraft.baked_potato":23,"stat.pickup.minecraft.oak_stairs":36,"stat.pickup.minecraft.trapdoor":11,"stat.useItem.minecraft.sandstone":120,"stat.useItem.minecraft.dark_oak_fence":91,"stat.killEntity.Silverfish":3,"stat.useItem.minecraft.redstone_ore":15,"stat.entityKilledBy.Zombie":1,"stat.pickup.minecraft.fence":222,"stat.pickup.minecraft.iron_pickaxe":10,"stat.pickup.minecraft.diamond_ore":29,"stat.drop.minecraft.sand":35,"stat.mineBlock.minecraft.quartz_ore":154,"stat.mineBlock.minecraft.stone":11981,"stat.mineBlock.minecraft.cobblestone_wall":1,"stat.minecartOneCm":697008,"stat.mineBlock.minecraft.dirt":7467,"stat.pickup.minecraft.spruce_fence":29,"stat.drop.minecraft.grass":1,"stat.mineBlock.minecraft.fence_gate":3,"stat.useItem.minecraft.armor_stand":4,"stat.killEntity.Blaze":12,"stat.pickup.minecraft.stained_glass":54,"stat.useItem.minecraft.spawn_egg":26,"stat.pickup.minecraft.dye":186,"stat.mineBlock.minecraft.dark_oak_stairs":61,"stat.craftItem.minecraft.iron_boots":4,"stat.pickup.minecraft.cooked_mutton":10,"stat.craftItem.minecraft.anvil":2,"stat.craftItem.minecraft.leather_leggings":2,"stat.useItem.minecraft.dark_oak_door":3,"stat.useItem.minecraft.diamond_axe":3976,"stat.useItem.minecraft.lava_bucket":30,"stat.useItem.minecraft.magma":1,"achievement.blazeRod":4,"stat.craftItem.minecraft.dark_oak_fence":99,"achievement.snipeSkeleton":1,"stat.useItem.minecraft.carpet":57,"stat.mineBlock.minecraft.glass_pane":1,"stat.useItem.minecraft.wooden_button":5,"stat.pickup.minecraft.potato":70,"stat.pickup.minecraft.redstone_torch":2,"stat.breakItem.minecraft.iron_pickaxe":15,"stat.mineBlock.minecraft.ladder":7,"stat.useItem.minecraft.cobblestone_wall":9,"stat.craftItem.minecraft.sign":33,"stat.mineBlock.minecraft.gravel":232,"stat.craftItem.minecraft.blaze_powder":8,"stat.useItem.minecraft.baked_potato":38,"stat.useItem.minecraft.stone_stairs":205,"stat.breakItem.minecraft.iron_helmet":1,"stat.mineBlock.minecraft.redstone_ore":175,"stat.useItem.minecraft.wooden_axe":9,"stat.useItem.minecraft.wooden_pickaxe":63,"stat.brewingstandInteraction":1,"stat.useItem.minecraft.cauldron":1,"stat.mineBlock.minecraft.ender_chest":2,"stat.pickup.minecraft.glowstone_dust":294,"stat.killEntity.Squid":5,"stat.pickup.minecraft.stone_sword":2,"stat.killEntity.CaveSpider":9,"stat.pickup.minecraft.leather_helmet":1,"stat.pickup.minecraft.iron_shovel":6,"stat.pickup.minecraft.red_mushroom":3,"stat.drop.minecraft.diamond_axe":2,"stat.pickup.minecraft.acacia_door":3,"stat.mineBlock.minecraft.coal_ore":1879,"stat.useItem.minecraft.bread":218,"stat.mineBlock.minecraft.log2":884,"stat.craftItem.minecraft.diamond_axe":4,"stat.pickup.minecraft.leather":66,"stat.entityKilledBy.Enderman":1,"stat.mineBlock.minecraft.tallgrass":447,"stat.craftItem.minecraft.stone_sword":3,"stat.pickup.minecraft.iron_helmet":6,"stat.pickup.minecraft.rail":30,"stat.pickup.minecraft.stone_slab":329,"stat.useItem.minecraft.iron_sword":1093,"stat.drop.minecraft.leaves":1,"stat.craftItem.minecraft.spruce_fence":177,"achievement.breedCow":32,"stat.pickup.minecraft.nether_brick_fence":8,"stat.craftItem.minecraft.crafting_table":24,"stat.mobKills":2861,"stat.craftItem.minecraft.diamond_shovel":8,"stat.useItem.minecraft.bucket":317,"stat.craftItem.minecraft.armor_stand":2,"stat.useItem.minecraft.string":2,"stat.killEntity.Zombie":1916,"stat.useItem.minecraft.sign":39,"stat.drop.minecraft.bucket":1,"stat.useItem.minecraft.bookshelf":105,"stat.craftItem.minecraft.glass_pane":336,"stat.pickup.minecraft.stonebrick":2653,"stat.useItem.minecraft.carrot":507,"stat.useItem.minecraft.trapdoor":45,"stat.drop.minecraft.stone_shovel":1,"stat.drop.minecraft.wheat":8,"stat.pickup.minecraft.bone":77,"stat.pickup.minecraft.wheat_seeds":2867,"stat.craftItem.minecraft.dark_oak_door":3,"stat.swimOneCm":533675,"stat.killEntity.Skeleton":91,"stat.pickup.minecraft.bread":19,"stat.breakItem.minecraft.leather_helmet":1,"stat.walkOneCm":22997358,"stat.pickup.minecraft.arrow":123,"stat.pickup.minecraft.double_plant":7,"stat.mineBlock.minecraft.oak_stairs":39,"stat.craftItem.minecraft.stone_brick_stairs":872,"stat.mineBlock.minecraft.lapis_ore":19,"stat.jump":80729,"stat.pickup.minecraft.dark_oak_stairs":56,"stat.craftItem.minecraft.stone":6316,"stat.useItem.minecraft.beacon":5,"stat.killEntity.Witch":2,"stat.useItem.minecraft.apple":9,"stat.craftItem.minecraft.lapis_block":13,"stat.drop.minecraft.dye":2,"stat.deaths":11,"stat.mineBlock.minecraft.glowstone":140,"stat.useItem.minecraft.wooden_slab":3714,"stat.drop.minecraft.slime_ball":1,"stat.mineBlock.minecraft.stained_glass_pane":22,"stat.pickup.minecraft.egg":3448,"stat.craftItem.minecraft.planks":5806,"stat.craftItem.minecraft.trapdoor":28,"stat.chestOpened":2591,"stat.pickup.minecraft.gunpowder":65,"stat.pickup.minecraft.diamond_axe":8,"stat.useItem.minecraft.diamond_hoe":20,"stat.itemEnchanted":56,"stat.pickup.minecraft.gold_ingot":87,"stat.craftItem.minecraft.shears":1,"stat.pickup.minecraft.cobblestone":8095,"stat.craftItem.minecraft.stained_glass":320,"stat.craftItem.minecraft.melon_block":78,"stat.craftItem.minecraft.diamond_helmet":1,"stat.useItem.minecraft.wooden_shovel":33,"stat.useItem.minecraft.iron_pickaxe":4623,"stat.pickup.minecraft.armor_stand":2,"stat.craftItem.minecraft.tnt":17,"stat.drop.minecraft.dirt":7,"stat.pickup.minecraft.obsidian":15,"stat.pickup.minecraft.waterlily":19,"stat.sprintOneCm":7985892,"stat.useItem.minecraft.dirt":5692,"stat.pickup.minecraft.diamond_boots":2}